transfunctions/__init__.py
transfunctions/errors.py
transfunctions/markers.py
transfunctions/py.typed
transfunctions/transformer.py
transfunctions/typing.py
transfunctions/universal_namespace.py
transfunctions/decorators/__init__.py
transfunctions/decorators/superfunction.py
transfunctions/decorators/transfunction.py
transfunctions-0.0.8.dist-info/LICENSE
transfunctions-0.0.8.dist-info/METADATA
transfunctions-0.0.8.dist-info/WHEEL
transfunctions-0.0.8.dist-info/top_level.txt
transfunctions-0.0.8.dist-info/RECORD
