Metadata-Version: 2.1
Name: transfunctions
Version: 0.0.8
Summary: Say NO to Python fragmentation on sync and async
Author-email: Evgeniy Blinov <zheni-b@yandex.ru>
Project-URL: Source, https://github.com/pomponchik/transfunctions
Project-URL: Tracker, https://github.com/pomponchik/transfunctions/issues
Keywords: async,sync to async,async to sync,code generation,ast manipulation,metaprogramming,magic
Classifier: Operating System :: OS Independent
Classifier: Operating System :: MacOS :: MacOS X
Classifier: Operating System :: Microsoft :: Windows
Classifier: Operating System :: POSIX
Classifier: Operating System :: POSIX :: Linux
Classifier: Programming Language :: Python
Classifier: Programming Language :: Python :: 3.8
Classifier: Programming Language :: Python :: 3.9
Classifier: Programming Language :: Python :: 3.10
Classifier: Programming Language :: Python :: 3.11
Classifier: Programming Language :: Python :: 3.12
Classifier: Programming Language :: Python :: 3.13
Classifier: License :: OSI Approved :: MIT License
Classifier: Intended Audience :: Developers
Classifier: Topic :: Software Development :: Libraries
Classifier: Topic :: Software Development :: Code Generators
Classifier: Framework :: AsyncIO
Requires-Python: >=3.8
License-File: LICENSE
Requires-Dist: displayhooks>=0.0.4
Requires-Dist: dill==0.4.0
Requires-Dist: typing-extensions; python_version <= "3.10"
